SQLGlassBoxFunction/SQLGlassBoxFunction.py
SQLGlassBoxFunction/__init__.py
SQLGlassBoxFunction/test_SQLGlassBoxFunction.py
SQLGlassBoxFunction-0.1.4.dist-info/METADATA
SQLGlassBoxFunction-0.1.4.dist-info/WHEEL
SQLGlassBoxFunction-0.1.4.dist-info/top_level.txt
SQLGlassBoxFunction-0.1.4.dist-info/RECORD
