Metadata-Version: 2.2
Name: SQLGlassBoxFunction
Version: 0.1.4
Summary: A package to provide glass box functions for SQL analysis
Home-page: https://github.com/gordil/SQL-glass-box-function
Author: Gordil
Author-email: gordil.tech@gmail.com
Classifier: Programming Language :: Python :: 3
Classifier: License :: OSI Approved :: MIT License
Classifier: Operating System :: OS Independent
Requires-Python: >=3.6
Dynamic: author
Dynamic: author-email
Dynamic: classifier
Dynamic: description
Dynamic: description-content-type
Dynamic: home-page
Dynamic: requires-python
Dynamic: summary
